ray_provider/__init__.py
ray_provider/decorators/__init__.py
ray_provider/decorators/ray_decorators.py
ray_provider/example_dags/__init__.py
ray_provider/example_dags/ray_pandas_example_dag.py
ray_provider/example_dags/task_flow_xgboost_modin.py
ray_provider/example_dags/xgboost_pandas_tune_breast_cancer.py
ray_provider/hooks/__init__.py
ray_provider/hooks/ray_client.py
ray_provider/xcom/__init__.py
ray_provider/xcom/ray_backend.py
airflow_provider_ray-0.2.1.dist-info/LICENSE
airflow_provider_ray-0.2.1.dist-info/METADATA
airflow_provider_ray-0.2.1.dist-info/WHEEL
airflow_provider_ray-0.2.1.dist-info/entry_points.txt
airflow_provider_ray-0.2.1.dist-info/top_level.txt
airflow_provider_ray-0.2.1.dist-info/RECORD
