Metadata-Version: 2.1
Name: airflow-provider-ray
Version: 0.2.1
Summary: An Apache Airflow provider for Ray
Home-page: UNKNOWN
Author: Rob Deeb, Richard Liaw, Daniel Imberman, Pete DeJoy
Author-email: rob@astronomer.io, daniel@astronomer.io, rliaw@anyscale.com, pete@astronomer.io
Maintainer: Rob Deeb, Richard Liaw, Daniel Imberman, Pete DeJoy
Maintainer-email: rob@astronomer.io, daniel@astronomer.io, rliaw@anyscale.com, pete@astronomer.io
License: Apache License 2.0
Keywords: ray,distributed,compute,airflow
Platform: UNKNOWN
Requires-Python: >=3.7
Requires-Dist: apache-airflow (>=2.0)
Requires-Dist: pandas (>=1.0.0)
Requires-Dist: filelock (>=3.0.0)
Requires-Dist: ray
